aiconfig_extension_hugging_face/__init__.py
aiconfig_extension_hugging_face/local_inference/automatic_speech_recognition.py
aiconfig_extension_hugging_face/local_inference/image_2_text.py
aiconfig_extension_hugging_face/local_inference/text_2_image.py
aiconfig_extension_hugging_face/local_inference/text_2_speech.py
aiconfig_extension_hugging_face/local_inference/text_generation.py
aiconfig_extension_hugging_face/local_inference/text_summarization.py
aiconfig_extension_hugging_face/local_inference/text_translation.py
aiconfig_extension_hugging_face/local_inference/util.py
aiconfig_extension_hugging_face/remote_inference_client/automatic_speech_recognition.py
aiconfig_extension_hugging_face/remote_inference_client/conversational.py
aiconfig_extension_hugging_face/remote_inference_client/image_2_text.py
aiconfig_extension_hugging_face/remote_inference_client/text_2_image.py
aiconfig_extension_hugging_face/remote_inference_client/text_2_speech.py
aiconfig_extension_hugging_face/remote_inference_client/text_generation.py
aiconfig_extension_hugging_face/remote_inference_client/text_summarization.py
aiconfig_extension_hugging_face/remote_inference_client/text_translation.py
aiconfig_extension_hugging_face-0.0.13.dist-info/LICENSE
aiconfig_extension_hugging_face-0.0.13.dist-info/METADATA
aiconfig_extension_hugging_face-0.0.13.dist-info/WHEEL
aiconfig_extension_hugging_face-0.0.13.dist-info/top_level.txt
aiconfig_extension_hugging_face-0.0.13.dist-info/RECORD
