Metadata-Version: 2.1
Name: aiconfig_extension_hugging_face
Version: 0.0.13
Summary: An extension for using Hugging Face tasks to parse models for AIConfig.
Author: LastMile AI
Author-email: Rossdan Craig <rossdan@lastmileai.dev>, Ankush Pala <ankush@lastmileai.dev>
Project-URL: Homepage, https://github.com/lastmile-ai/aiconfig/
Project-URL: Issues, https://github.com/lastmile-ai/aiconfig/issues
Classifier: Programming Language :: Python :: 3
Classifier: License :: OSI Approved :: MIT License
Classifier: Operating System :: OS Independent
Requires-Python: >=3.10
License-File: LICENSE
Requires-Dist: black
Requires-Dist: pylint
Requires-Dist: python-aiconfig
Requires-Dist: huggingface-hub >=0.20.3
Requires-Dist: accelerate
Requires-Dist: diffusers
Requires-Dist: sacremoses
Requires-Dist: scipy
Requires-Dist: sentencepiece
Requires-Dist: torch
Requires-Dist: torchvision
Requires-Dist: torchaudio
Requires-Dist: transformers
Requires-Dist: asyncio
